{"attachmentList": [{"code": "BK_PLTTB", "fileList": [{"id": 0, "name": "2. BAN PHAN LOAI.pdf", "url": "https://dmec.moh.gov.vn/documents/10182/18885171/upload_00021336_1616460979123.pdf?version=1.0&fileId=18885329"}], "id": "1", "name": "Bản phân loại trang thiết bị y tế"}, {"code": "GCN_TCCL", "fileList": [{"id": 0, "name": "3. ISO 13485-2020.pdf", "url": "https://dmec.moh.gov.vn/documents/10182/18885171/upload_00021340_1616460986542.pdf?version=1.0&fileId=18885337"}], "id": "2", "name": "Giấy chứng nhận đạt tiêu chuẩn quản lý chất lượng"}, {"code": "GUQ_TTBYT", "fileList": [{"id": 0, "name": "4. GIAY UY QUYEN VA BAO HANH PLAIN CATGUT CO KIM.pdf", "url": "https://dmec.moh.gov.vn/documents/10182/18885171/upload_00021344_1616460995281.pdf?version=1.0&fileId=18885345"}], "id": "3", "name": "Giấy ủy quyền của chủ sở hữu trang thiết bị y tế"}, {"code": "CNLH", "fileList": [{"id": 0, "name": "9. PTN CONG BO DU DIEU KIEN SX TTBYT.pdf", "url": "https://dmec.moh.gov.vn/documents/10182/18885171/upload_00021352_1616461012935.pdf?version=1.0&fileId=18885361"}], "id": "5", "name": "Giấy chứng nhận lưu hành tự do còn hiệu lực tại thời điểm nộp hồ sơ đối với trang thiết bị y tế nhập khẩu hoặc Phiếu tiếp nhận hồ sơ công bố đủ điều kiện sản xuất trang thiết bị y tế đối với TTBYT sản xuất trong nước"}], "equipment": {"equipmentList": [{"code": "1152902", "factoryList": [{"address": "- Địa chỉ chủ sở hữu: 31 Ngô Thời Nhiệm, phường Võ Thị Sáu, quận 3, TP. Hồ Chí Minh - Địa chỉ cơ sở sản xuất: Lô III-18, đường số 13, KCN Tân Bình, P. Tây Thạnh, Q. Tân Phú,  TP. Hồ Chí Minh.", "country": "20434", "name": "CÔNG TY CỔ PHẦN DƯỢC PHẨM VÀ SINH HỌC Y TẾ"}], "iso": "13485:2016", "name": "Plain catgut, kim", "packing": null, "type": "213502"}], "group": 0, "medicalEquipmentType": 3, "name": "Chỉ khâu phẫu thuật tự tiêu,  có gắn kim", "singleUse": 0}, "equipmentOwner": {"address": "- Địa chỉ chủ sở hữu: 31 Ngô Thời Nhiệm, phường Võ Thị Sáu, quận 3, TP. Hồ Chí Minh - Địa chỉ cơ sở sản xuất: Lô III-18, đường số 13, KCN Tân Bình, P. Tây Thạnh, Q. Tân Phú,  TP. Hồ Chí Minh.", "country": "20434", "name": "CÔNG TY CỔ PHẦN DƯỢC PHẨM VÀ SINH HỌC Y TẾ"}, "fastTrack": false, "profileCode": "string", "profileId": 0, "profileOwner": "string", "registrant": {"address": "31 Ngô Thời Nhiệm, Phường Võ Thị Sáu, Quận 3, Thành phố Hồ Chí Minh, Việt Nam", "email": "mebiphar@mebiphar.com", "fax": "02838155683", "name": "CÔNG TY CỔ PHẦN DƯỢC PHẨM VÀ SINH HỌC Y TẾ", "phone": "02839303894", "taxCode": "0300533351"}, "representator": {"identifier": "Đinh Anh Hào", "issuedBy": "string", "issuedDate": "2021-07-25", "mobilePhone": "string", "name": "string", "phone": "string"}, "serviceCode": "string", "serviceName": "string", "submittedAt": "2021-07-25T12:10:15.668Z", "warrantyFacilityList": [{"address": "string", "mobilePhone": "string", "name": "string", "phone": "string", "taxCode": "string"}]}