{"attachmentList": [{"code": "BK_PLTTB", "fileList": [{"id": 0, "name": "Ban phan loai.pdf", "url": "https://dmec.moh.gov.vn/documents/10182/19102087/upload_00018491_1617613688403.pdf?version=1.0&fileId=19113759"}], "id": "1", "name": "Bản phân loại trang thiết bị y tế"}, {"code": "GCN_TCCL", "fileList": [{"id": 0, "name": "Giay chung nhan ISO, GMP.pdf", "url": "https://dmec.moh.gov.vn/documents/10182/19102087/upload_00018495_1617613701122.pdf?version=1.0&fileId=19113767"}], "id": "2", "name": "Giấy chứng nhận đạt tiêu chuẩn quản lý chất lượng"}, {"code": "GUQ_TTBYT", "fileList": [{"id": 0, "name": "CV xac nhan chu so huu TTBYT.pdf", "url": "https://dmec.moh.gov.vn/documents/10182/19117679/upload_00033178_1617682068916.pdf?version=1.0&fileId=19124310"}], "id": "3", "name": "Giấy ủy quyền của chủ sở hữu trang thiết bị y tế"}, {"code": "CNLH", "fileList": [{"id": 0, "name": "PTN_ ĐKSX_USM.pdf", "url": "https://dmec.moh.gov.vn/documents/10182/19117679/upload_00040686_1617694606330.pdf?version=1.0&fileId=19128796"}], "id": "5", "name": "Giấy chứng nhận lưu hành tự do còn hiệu lực tại thời điểm nộp hồ sơ đối với trang thiết bị y tế nhập khẩu hoặc Phiếu tiếp nhận hồ sơ công bố đủ điều kiện sản xuất trang thiết bị y tế đối với TTBYT sản xuất trong nước"}, {"code": "FASTTRACK3", "fileList": [{"id": 0, "name": "GPLH da duoc cap.pdf", "url": "https://dmec.moh.gov.vn/documents/10182/19117679/upload_00033630_1617682569478.pdf?version=1.0&fileId=19124834"}], "id": "9", "name": "Giấy chứng nhận lưu hành tự do của một trong các nước hoặc tổ chức sau: Các nước thành viên EU, Nhật Bản, Ca-na-đa, TGA của Úc, FDA của Mỹ(Bắt buộc đối với trường hợp 1 cấp nhanh số lưu hành)"}], "equipment": {"equipmentList": [{"code": "1156195", "factoryList": [{"address": "Lô I-4b-1.3, Đường N3, Khu Công nghệ cao, phường Long Thạnh Mỹ, Tp. Thủ Đức, Tp. Hồ Chí Minh", "country": "20434", "name": "CÔNG TY CỔ PHẦN NHÀ MÁY TRANG THIẾT BỊ Y TẾ USM HEALTHCARE"}], "iso": "13485:2016", "name": "VENTKING", "packing": null, "type": "213505"}], "group": 0, "medicalEquipmentType": 1, "name": "Ống nối dây máy thở cao tần", "singleUse": 0}, "equipmentOwner": {"address": "Lô I-4b-1.3, Đường N3, Khu Công nghệ cao, phường Long Thạnh Mỹ, Tp. Thủ Đức, Tp. Hồ Chí Minh", "country": "20434", "name": "CÔNG TY CỔ PHẦN NHÀ MÁY TRANG THIẾT BỊ Y TẾ USM HEALTHCARE"}, "fastTrack": true, "profileCode": "string", "profileId": 0, "profileOwner": "string", "registrant": {"address": "Lô I - 4b - 1.3, Đường N3, khu Công nghệ cao", "email": "info@usm.com.vn", "fax": "02873043888", "name": "CÔNG TY CỔ PHẦN NHÀ MÁY TRANG THIẾT BỊ Y TẾ USM HEALTHCARE", "phone": "02873044888", "taxCode": "0312041033"}, "representator": {"identifier": "Võ Xuân Bội Lâm", "issuedBy": "string", "issuedDate": "2021-07-25", "mobilePhone": "string", "name": "string", "phone": "string"}, "serviceCode": "string", "serviceName": "string", "submittedAt": "2021-07-25T12:10:15.668Z", "warrantyFacilityList": [{"address": "string", "mobilePhone": "string", "name": "string", "phone": "string", "taxCode": "string"}]}