[{"commentContent": "C\u00f4ng ty s\u1ea3n xu\u1ea5t kh\u00f4ng h\u1ee3p l\u1ec7", "commentStatus": "NOK", "detail": [" xu\u00e1t \u0111\u1ec3 xu\u1ea5t kh\u1ea9u th\u1ec9\u1ebft b\u1ecb y t\u1ebf n\u00f3i tr\u00ean sang c\u00e1c qu\u1ed1c gia ngo\u00e0i li\u00ean minh ch\u00e2u \u00c2u. page 5"]}, {"commentContent": "C\u00f4ng ty s\u1edf h\u1eefu kh\u00f4ng h\u1ee3p l\u1ec7", "commentStatus": "NOK", "detail": [" MEDICAL DEVICE SCHEDULE page 14"]}, {"commentContent": "Danh s\u00e1ch TTBYT \u0111\u1ea7y \u0111\u1ee7", "commentStatus": "OK", "detail": [[" L2u-aspnac350 BASIC 5 Refre *10356/39 SuRGICALSuCiONUNis page 10"]]}, {"commentContent": "Danh s\u00e1ch m\u00e3 TTBYT \u0111\u1ea7y \u0111\u1ee7", "commentStatus": "OK", "detail": [["  8 7 | 1 | 5 1 5 | 4 3 1 1 1 { 5 1 5 K) = J =  2 = 4 5 2 1 2 2  4 ; ! 4 1 1 2 page 14"], [" BO HUT PHAU THUAT S-S6BR REF RE 4o2/0/0 | page 4"], ["  page 8"], [" 4 page 12"], ["  page 7"], [" 5-20 ONG NGHE REFSTIOOOO] page 5"], ["  8 7 | 1 | 5 1 5 | 4 3 1 1 1 { 5 1 5 K) = J =  2 = 4 5 2 1 2 2  4 ; ! 4 1 1 2 page 14"]]}, {"commentContent": "Th\u1eddi gian h\u1ebft hi\u1ec7u l\u1ef1c", "commentStatus": "NOK", "valid_date": [" Immulite 2000 Specific Allergen Date Palm t406, 20 size SMN 10386091 PIN T406L2 page 15", " websites - Itis onlyallowed to show OF to dclivery ilupon (cquest of thc Customs Or Heallh competent page 12", " To RefTr 200100 ElcMoNIC Thermomever page 12", " CERTIFICATE OF FREE SALE FOR EXPORTATION OF MEDICAL PRODUCTS TO page 1"], "begin_date": [" PH\u00d2NG TH\u01af\u01a0NG MAICONG NGHIEP THU CONG NGHIEP VA NONG NGHIEP PARMA Ch\u1ee9ng nh\u1eadn v\u0103n ban \u0111\u01b0\u1ee3c l\u01b0u t\u1ea1i Phong nay. So: 93 Ng\u00e0y /1/02/2019 Vi\u00ean ch\u00fac hanh chinh Eleonora Ariu \u0110\u00e3 k\u1ef7 v\u00e0 \u0111\u00f3ng dau page 7", " C\u01a0 OUAN DAI DI\u1ebaN CHINH PHU TAI PARMA H\u1ee3p ph\u00e1p h\u00f3a ch\u1eef k\u00fd v\u00e0 th\u1ea9m quy\u00e8n k\u00fd c\u1ee7a b\u00e0 Eleonora  Ariu; Vi\u00ean ch\u1ee9c Ph\u00f2ng Thuong m\u1ea1i Parma th\u1eeba \u1ee7y quy\u00ean cua B\u1ed9 Ngoai giao theo \u0111i\u1ec1u 4 Lu\u00e2t L/5/1971 s6 390. Parma, ng\u00e0y 12/02/2019 Vi\u00ean ch\u1eedc d\u01b0\u1ee3c \u1ee7y quy\u1ec1n Costanza Trenta (\u0111\u00e3k\u00fd. \u0111\u00f3ng d\u1ea5u) page 7", " Immulite 2000 Specific Allergen Date Palm t406, 20 size SMN 10386091 PIN T406L2 page 15"], "period": [" Control for D1 page 18", " Ullacnnza 2do One (Ba) (L has been cianed o CanX_lanh Bu 3 vm chuc danh Fecting In the capacity ot n 4va con dau cua bears (he seallslamp 0i K page 3"]}, {"commentContent": "C\u00f3 d\u1ea5u l\u00e3nh s\u1ee9 qu\u00e1n (trang 10)", "commentStatus": "OK"}]